mpt/__init__.py
mpt/db.py
mpt/trie.py
mpt/utils.py
ethereum_merkle_patricia_trie-0.0.3.dist-info/METADATA
ethereum_merkle_patricia_trie-0.0.3.dist-info/WHEEL
ethereum_merkle_patricia_trie-0.0.3.dist-info/top_level.txt
ethereum_merkle_patricia_trie-0.0.3.dist-info/RECORD
